[{"__type__":"cc.SpriteFrame","content":{"name":"level_star_1_1","texture":"3b6xqYynJEW41qbTs1QJpv","rect":[50,892,46,46],"offset":[0,0],"originalSize":[46,46],"capInsets":[0,0,0,0]}},{"__type__":"cc.SpriteFrame","content":{"name":"weapon_gun","texture":"3b6xqYynJEW41qbTs1QJpv","rect":[608,746,44,24],"offset":[0,0],"originalSize":[44,24],"rotated":1,"capInsets":[0,0,0,0]}},{"__type__":"cc.SpriteFrame","content":{"name":"hp_up_01","texture":"3b6xqYynJEW41qbTs1QJpv","rect":[1013,232,63,6],"offset":[0,0],"originalSize":[63,6],"rotated":1,"capInsets":[0,0,0,0]}},[{"__type__":"cc.Prefab","_name":"Player","data":{"__id__":1},"optimizationPolicy":1},{"__type__":"cc.Node","_name":"Player","_children":[{"__id__":2},{"__id__":4},{"__id__":6},{"__id__":17},{"__id__":21}],"_components":[{"__type__":"175c9l71jJIOK/erMuxWhel","node":{"__id__":1},"roleAnim":{"__id__":3},"_gunDir":{"__type__":"cc.Vec2","y":1},"gunAnim":{"__id__":5},"gunNode":{"__id__":4},"gunData":{},"skinData":{},"nameUI":{"__id__":8},"bulletPrefab":{"__uuid__":"1bWFgR4INEVbxUX0hDnsDT"},"hpBar":{"__id__":16},"amoBar":{"__id__":15},"starNode":{"__id__":21},"_aimInterval":0.1,"arrowNode":{"__id__":18}},{"__type__":"cc.RigidBody","node":{"__id__":1},"_allowSleep":false,"_gravityScale":0,"_fixedRotation":true,"enabledContactListener":true,"bullet":true},{"__type__":"cc.PhysicsBoxCollider","node":{"__id__":1},"tag":1,"_sensor":true,"_friction":0,"_offset":{"__type__":"cc.Vec2","x":-1.1,"y":54.1},"_size":{"__type__":"cc.Size","width":48.5,"height":88}},{"__type__":"cc.PhysicsBoxCollider","node":{"__id__":1},"tag":4,"_friction":0,"_offset":{"__type__":"cc.Vec2","y":11.2},"_size":{"__type__":"cc.Size","width":35.400000000000006,"height":31.1}}],"_prefab":{"__type__":"cc.PrefabInfo","root":{"__id__":1},"asset":{"__uuid__":"4c+6i3tK1Ciq/LlXv5yJZX"},"fileId":"8075PEn+hOm6UlFt801LsA"},"_trs":{"__type__":"TypedArray","ctor":"Float64Array","array":[0,0,0,0,0,0,1,1,1,1]},"_groupIndex":3,"groupIndex":3},{"__type__":"cc.Node","_name":"Player","_parent":{"__id__":1},"_components":[{"__id__":3}],"_prefab":{"__type__":"cc.PrefabInfo","root":{"__id__":1},"asset":{"__uuid__":"4c+6i3tK1Ciq/LlXv5yJZX"},"fileId":"19177MsLJGBoabOsBMP3Oa"},"_contentSize":{"__type__":"cc.Size","width":93.26,"height":135.46},"_trs":{"__type__":"TypedArray","ctor":"Float64Array","array":[0,0,0,0,0,0,1,1,1,1]},"_groupIndex":3,"groupIndex":3},{"__type__":"sp.Skeleton","node":{"__id__":2},"_materials":[{"__uuid__":"7a/QZLET9IDreTiBfRn2PD"}],"defaultSkin":"runningDeadGirl1","defaultAnimation":"await","_preCacheMode":0,"premultipliedAlpha":false,"_animationName":"await","_N$skeletonData":{"__uuid__":"c8J2f/i+1DJaroVwhNARR2"}},{"__type__":"cc.Node","_name":"Gun","_parent":{"__id__":1},"_children":[{"__type__":"cc.Node","_name":"Pos","_parent":{"__id__":4},"_prefab":{"__type__":"cc.PrefabInfo","root":{"__id__":1},"asset":{"__uuid__":"4c+6i3tK1Ciq/LlXv5yJZX"},"fileId":"5a53lQfd1FPr7qlwonaESg"},"_trs":{"__type__":"TypedArray","ctor":"Float64Array","array":[41.287,0,0,0,0,0,1,1,1,1]},"_groupIndex":3,"groupIndex":3}],"_active":false,"_components":[{"__id__":5}],"_prefab":{"__type__":"cc.PrefabInfo","root":{"__id__":1},"asset":{"__uuid__":"4c+6i3tK1Ciq/LlXv5yJZX"},"fileId":"f2UsX5Uc9OgLxp/2+Fjlbb"},"_contentSize":{"__type__":"cc.Size","width":64.12,"height":39.07},"_trs":{"__type__":"TypedArray","ctor":"Float64Array","array":[0,29.499,0,0,0,0,1,1,1,1]},"_groupIndex":3,"groupIndex":3},{"__type__":"sp.Skeleton","node":{"__id__":4},"_materials":[{"__uuid__":"7a/QZLET9IDreTiBfRn2PD"}],"_preCacheMode":0,"loop":false,"premultipliedAlpha":false,"_animationName":"reload_1105","_playTimes":1},{"__type__":"cc.Node","_name":"TopNode","_parent":{"__id__":1},"_children":[{"__id__":7},{"__id__":9}],"_components":[{"__type__":"cc.Layout","node":{"__id__":6},"_layoutSize":{"__type__":"cc.Size","width":86,"height":59.5},"_resize":1,"_N$layoutType":2}],"_prefab":{"__type__":"cc.PrefabInfo","root":{"__id__":1},"asset":{"__uuid__":"4c+6i3tK1Ciq/LlXv5yJZX"},"fileId":"57yRzQFeJNnIjpRePoF4wx"},"_contentSize":{"__type__":"cc.Size","width":86,"height":59.5},"_anchorPoint":{"__type__":"cc.Vec2","x":0.5},"_trs":{"__type__":"TypedArray","ctor":"Float64Array","array":[0,117.36,0,0,0,0,1,1,1,1]},"_groupIndex":3,"groupIndex":3},{"__type__":"cc.Node","_name":"text_name","_parent":{"__id__":6},"_components":[{"__id__":8},{"__type__":"cc.LabelOutline","node":{"__id__":7},"_color":{"__type__":"cc.Color"},"_width":3}],"_prefab":{"__type__":"cc.PrefabInfo","root":{"__id__":1},"asset":{"__uuid__":"4c+6i3tK1Ciq/LlXv5yJZX"},"fileId":"99gai1AotLnYK+K9hM25Sk"},"_color":{"__type__":"cc.Color","r":9,"g":178,"b":235},"_contentSize":{"__type__":"cc.Size","width":86,"height":37.5},"_trs":{"__type__":"TypedArray","ctor":"Float64Array","array":[0,40.75,0,0,0,0,1,1,1,1]},"_groupIndex":3,"groupIndex":3},{"__type__":"cc.Label","node":{"__id__":7},"_materials":[{"__uuid__":"ecpdLyjvZBwrvm+cedCcQy"}],"_string":"菠萝吹雪","_N$string":"菠萝吹雪","_fontSize":20,"_lineHeight":25,"_N$horizontalAlign":1,"_N$verticalAlign":1},{"__type__":"cc.Node","_name":"HpBar","_parent":{"__id__":6},"_children":[{"__id__":10},{"__id__":12}],"_components":[{"__type__":"cc.Sprite","node":{"__id__":9},"_materials":[{"__uuid__":"ecpdLyjvZBwrvm+cedCcQy"}],"_spriteFrame":{"__uuid__":"8dlyI0OOhPR78Ya4RYSLgV"},"_sizeMode":2,"_isTrimmedMode":false},{"__id__":16}],"_prefab":{"__type__":"cc.PrefabInfo","root":{"__id__":1},"asset":{"__uuid__":"4c+6i3tK1Ciq/LlXv5yJZX"},"fileId":"36lkDSqqtLzZutxzMSVwMR"},"_contentSize":{"__type__":"cc.Size","width":83,"height":22},"_trs":{"__type__":"TypedArray","ctor":"Float64Array","array":[0,11,0,0,0,0,1,1,1,1]},"_groupIndex":3,"groupIndex":3},{"__type__":"cc.Node","_name":"bar","_parent":{"__id__":9},"_components":[{"__id__":11}],"_prefab":{"__type__":"cc.PrefabInfo","root":{"__id__":1},"asset":{"__uuid__":"4c+6i3tK1Ciq/LlXv5yJZX"},"fileId":"77B9BvGUFAk4/8RKGPs+Vr"},"_contentSize":{"__type__":"cc.Size","width":77,"height":10},"_anchorPoint":{"__type__":"cc.Vec2","y":0.5},"_trs":{"__type__":"TypedArray","ctor":"Float64Array","array":[-39.038,4.309,0,0,0,0,1,1,1,1]},"_groupIndex":3,"groupIndex":3},{"__type__":"cc.Sprite","node":{"__id__":10},"_materials":[{"__uuid__":"ecpdLyjvZBwrvm+cedCcQy"}],"_spriteFrame":{"__uuid__":"5eSP3zXqROloO3JwfRBJ3h"},"_type":3,"_sizeMode":0,"_fillRange":1,"_isTrimmedMode":false},{"__type__":"cc.Node","_name":"AmoBar","_parent":{"__id__":9},"_children":[{"__id__":13}],"_components":[{"__id__":15}],"_prefab":{"__type__":"cc.PrefabInfo","root":{"__id__":1},"asset":{"__uuid__":"4c+6i3tK1Ciq/LlXv5yJZX"},"fileId":"79tDZ+eWxIjYaciDANturq"},"_contentSize":{"__type__":"cc.Size","width":63,"height":10},"_trs":{"__type__":"TypedArray","ctor":"Float64Array","array":[-1.32,-5.077,0,0,0,0,1,1,1,1]},"_groupIndex":3,"groupIndex":3},{"__type__":"cc.Node","_name":"bar","_parent":{"__id__":12},"_components":[{"__id__":14}],"_prefab":{"__type__":"cc.PrefabInfo","root":{"__id__":1},"asset":{"__uuid__":"4c+6i3tK1Ciq/LlXv5yJZX"},"fileId":"3bKWlspThCr6tCtCMZuMAs"},"_contentSize":{"__type__":"cc.Size","width":63,"height":6},"_anchorPoint":{"__type__":"cc.Vec2","y":0.5},"_trs":{"__type__":"TypedArray","ctor":"Float64Array","array":[-31.5,0,0,0,0,0,1,1,1,1]},"_groupIndex":3,"groupIndex":3},{"__type__":"cc.Sprite","node":{"__id__":13},"_materials":[{"__uuid__":"ecpdLyjvZBwrvm+cedCcQy"}],"_spriteFrame":{"__uuid__":"34Fw4cO7NIOrUSw79UqPZJ"},"_type":3,"_sizeMode":2,"_fillRange":1,"_isTrimmedMode":false},{"__type__":"cc.ProgressBar","node":{"__id__":12},"_N$barSprite":{"__id__":14},"_N$mode":2},{"__type__":"cc.ProgressBar","node":{"__id__":9},"_N$barSprite":{"__id__":11},"_N$mode":2},{"__type__":"cc.Node","_name":"StandardNode","_parent":{"__id__":1},"_children":[{"__id__":18}],"_prefab":{"__type__":"cc.PrefabInfo","root":{"__id__":1},"asset":{"__uuid__":"4c+6i3tK1Ciq/LlXv5yJZX"},"fileId":"12B/rikK1MPqEpSJyDBnxg"},"_contentSize":{"__type__":"cc.Size","width":90,"height":120},"_anchorPoint":{"__type__":"cc.Vec2","x":0.5},"_trs":{"__type__":"TypedArray","ctor":"Float64Array","array":[0,20,0,0,0,0,1,1,1,1]},"_groupIndex":3,"groupIndex":3},{"__type__":"cc.Node","_name":"Arrow","_parent":{"__id__":17},"_children":[{"__id__":19}],"_active":false,"_prefab":{"__type__":"cc.PrefabInfo","root":{"__id__":1},"asset":{"__uuid__":"4c+6i3tK1Ciq/LlXv5yJZX"},"fileId":"15XXiE7dhK4ZrRpeTBlp1F"},"_trs":{"__type__":"TypedArray","ctor":"Float64Array","array":[100,0,0,0,0,0,1,1,1,1]},"_groupIndex":3,"groupIndex":3},{"__type__":"cc.Node","_name":"1","_parent":{"__id__":18},"_children":[{"__id__":20}],"_components":[{"__type__":"cc.Sprite","node":{"__id__":19},"_materials":[{"__uuid__":"ecpdLyjvZBwrvm+cedCcQy"}],"_spriteFrame":{"__uuid__":"2fX39n5W5NJoqU8SPhS5ku"},"_sizeMode":2,"_isTrimmedMode":false}],"_prefab":{"__type__":"cc.PrefabInfo","root":{"__id__":1},"asset":{"__uuid__":"4c+6i3tK1Ciq/LlXv5yJZX"},"fileId":"e1Z9E7C15EPrt7+f5cQwR7"},"_contentSize":{"__type__":"cc.Size","width":44,"height":24},"_trs":{"__type__":"TypedArray","ctor":"Float64Array","array":[0,0,0,0,0,0,1,1,1,1]},"_groupIndex":3,"groupIndex":3},{"__type__":"cc.Node","_name":"2","_parent":{"__id__":19},"_components":[{"__type__":"cc.Sprite","node":{"__id__":20},"_materials":[{"__uuid__":"ecpdLyjvZBwrvm+cedCcQy"}],"_spriteFrame":{"__uuid__":"e97iC8Oj5OVJCki7zzTXLx"},"_sizeMode":2,"_isTrimmedMode":false}],"_prefab":{"__type__":"cc.PrefabInfo","root":{"__id__":1},"asset":{"__uuid__":"4c+6i3tK1Ciq/LlXv5yJZX"},"fileId":"d0XOVPNmdMsp/CgS739+aO"},"_contentSize":{"__type__":"cc.Size","width":36,"height":54},"_trs":{"__type__":"TypedArray","ctor":"Float64Array","array":[30,0,0,0,0,0,1,1,1,1]},"_groupIndex":3,"groupIndex":3},{"__type__":"cc.Node","_name":"StarNode","_parent":{"__id__":1},"_children":[{"__id__":22},{"__id__":23}],"_active":false,"_prefab":{"__type__":"cc.PrefabInfo","root":{"__id__":1},"asset":{"__uuid__":"4c+6i3tK1Ciq/LlXv5yJZX"},"fileId":"6aGjZN40NE4JVLrsLYjLI/"},"_contentSize":{"__type__":"cc.Size","width":46,"height":46},"_trs":{"__type__":"TypedArray","ctor":"Float64Array","array":[-68.057,138.795,0,0,0,0,1,1,1,1]},"_groupIndex":3,"groupIndex":3},{"__type__":"cc.Node","_name":"bg","_parent":{"__id__":21},"_components":[{"__type__":"cc.Sprite","node":{"__id__":22},"_materials":[{"__uuid__":"ecpdLyjvZBwrvm+cedCcQy"}],"_spriteFrame":{"__uuid__":"97n1ZxtpNGCrRVqyN8ZN4W"},"_sizeMode":2,"_isTrimmedMode":false}],"_prefab":{"__type__":"cc.PrefabInfo","root":{"__id__":1},"asset":{"__uuid__":"4c+6i3tK1Ciq/LlXv5yJZX"},"fileId":"3bK6ZdZslEPZs70iXM8koB"},"_contentSize":{"__type__":"cc.Size","width":46,"height":46},"_trs":{"__type__":"TypedArray","ctor":"Float64Array","array":[0,2.144,0,0,0,0,1,1,1,1]},"_groupIndex":3,"groupIndex":3},{"__type__":"cc.Node","_name":"star","_parent":{"__id__":21},"_components":[{"__type__":"cc.Sprite","node":{"__id__":23},"_materials":[{"__uuid__":"ecpdLyjvZBwrvm+cedCcQy"}],"_spriteFrame":{"__uuid__":"09jGdn4apB/J+ZtYkeV3c5"},"_sizeMode":2,"_isTrimmedMode":false}],"_prefab":{"__type__":"cc.PrefabInfo","root":{"__id__":1},"asset":{"__uuid__":"4c+6i3tK1Ciq/LlXv5yJZX"},"fileId":"12OgunNglH94PozJWd30Aj"},"_contentSize":{"__type__":"cc.Size","width":46,"height":46},"_trs":{"__type__":"TypedArray","ctor":"Float64Array","array":[0,2.144,0,0,0,0,1,1,1,1]},"_groupIndex":3,"groupIndex":3}],{"__type__":"cc.SpriteFrame","content":{"name":"hp_up","texture":"3b6xqYynJEW41qbTs1QJpv","rect":[1012,364,77,10],"offset":[0,0],"originalSize":[77,10],"rotated":1,"capInsets":[0,0,0,0]}},{"__type__":"cc.SpriteFrame","content":{"name":"hp_down","texture":"3b6xqYynJEW41qbTs1QJpv","rect":[733,469,83,22],"offset":[0,0],"originalSize":[83,22],"capInsets":[0,0,0,0]}},{"__type__":"cc.SpriteFrame","content":{"name":"level_bg_1","texture":"3b6xqYynJEW41qbTs1QJpv","rect":[146,845,46,46],"offset":[0,0],"originalSize":[46,46],"capInsets":[0,0,0,0]}},{"__type__":"cc.SpriteFrame","content":{"name":"weapon_sign","texture":"3b6xqYynJEW41qbTs1QJpv","rect":[479,561,36,54],"offset":[0,0],"originalSize":[36,54],"capInsets":[0,0,0,0]}}]